lestari_classifier/__init__.py
lestari_classifier/classifier.py
lestari_classifier-0.1.3.dist-info/METADATA
lestari_classifier-0.1.3.dist-info/WHEEL
lestari_classifier-0.1.3.dist-info/top_level.txt
lestari_classifier-0.1.3.dist-info/RECORD
