Metadata-Version: 2.1
Name: lestari-classifier
Version: 0.1.3
Summary: An ensemble classifier that combines multiple base models using learned weights
Home-page: https://github.com/arifinrio95/lestari-classifier
Author: Rio Nur Arifin
Author-email: arifinrio95@gmail.com
Classifier: Programming Language :: Python :: 3
Classifier: License :: OSI Approved :: MIT License
Classifier: Operating System :: OS Independent
Classifier: Intended Audience :: Science/Research
Classifier: Topic :: Scientific/Engineering :: Artificial Intelligence
Requires-Python: >=3.7
Requires-Dist: numpy>=1.19.0
Requires-Dist: scikit-learn>=0.24.0
Requires-Dist: catboost>=0.24
Requires-Dist: lightgbm>=3.0.0
